[{"id":8,"name":"Accesorios para Vehículos","description":null,"created_at":"2025-11-24 15:35:17.683691","updated_at":"2025-11-25 07:07:11.902","ml_category_id":"MLA5725","is_ml_official":false,"is_leaf":false},{"id":9,"name":"Agro","description":null,"created_at":"2025-11-24 15:35:18.103959","updated_at":"2025-11-25 07:07:11.902","ml_category_id":"MLA1512","is_ml_official":false,"is_leaf":false},{"id":10,"name":"Alimentos y Bebidas","description":null,"created_at":"2025-11-24 15:35:18.504683","updated_at":"2025-11-25 07:07:11.902","ml_category_id":"MLA1403","is_ml_official":false,"is_leaf":false},{"id":11,"name":"Animales y Mascotas","description":null,"created_at":"2025-11-24 15:35:18.904034","updated_at":"2025-11-25 07:07:11.902","ml_category_id":"MLA1071","is_ml_official":false,"is_leaf":false},{"id":12,"name":"Antigüedades y Colecciones","description":null,"created_at":"2025-11-24 15:35:19.30835","updated_at":"2025-11-25 07:07:11.902","ml_category_id":"MLA1367","is_ml_official":false,"is_leaf":false},{"id":13,"name":"Arte, Librería y Mercería","description":null,"created_at":"2025-11-24 15:35:19.707521","updated_at":"2025-11-25 07:07:11.902","ml_category_id":"MLA1368","is_ml_official":false,"is_leaf":false},{"id":14,"name":"Autos, Motos y Otros","description":null,"created_at":"2025-11-24 15:35:20.107775","updated_at":"2025-11-25 07:07:11.902","ml_category_id":"MLA1743","is_ml_official":false,"is_leaf":false},{"id":15,"name":"Bebés","description":null,"created_at":"2025-11-24 15:35:20.512962","updated_at":"2025-11-25 07:07:11.902","ml_category_id":"MLA1384","is_ml_official":false,"is_leaf":false},{"id":16,"name":"Belleza y Cuidado Personal","description":null,"created_at":"2025-11-24 15:35:20.912123","updated_at":"2025-11-25 07:07:11.902","ml_category_id":"MLA1246","is_ml_official":false,"is_leaf":false},{"id":17,"name":"Cámaras y Accesorios","description":null,"created_at":"2025-11-24 15:35:21.312384","updated_at":"2025-11-25 07:07:11.902","ml_category_id":"MLA1039","is_ml_official":false,"is_leaf":false},{"id":18,"name":"Celulares y Teléfonos","description":null,"created_at":"2025-11-24 15:35:21.711723","updated_at":"2025-11-25 07:07:11.902","ml_category_id":"MLA1051","is_ml_official":false,"is_leaf":false},{"id":19,"name":"Computación","description":null,"created_at":"2025-11-24 15:35:22.11182","updated_at":"2025-11-25 07:07:11.902","ml_category_id":"MLA1648","is_ml_official":false,"is_leaf":false},{"id":20,"name":"Consolas y Videojuegos","description":null,"created_at":"2025-11-24 15:35:22.512106","updated_at":"2025-11-25 07:07:11.902","ml_category_id":"MLA1144","is_ml_official":false,"is_leaf":false},{"id":21,"name":"Construcción","description":null,"created_at":"2025-11-24 15:35:22.916161","updated_at":"2025-11-25 07:07:11.902","ml_category_id":"MLA1500","is_ml_official":false,"is_leaf":false},{"id":22,"name":"Deportes y Fitness","description":null,"created_at":"2025-11-24 15:35:23.316427","updated_at":"2025-11-25 07:07:11.902","ml_category_id":"MLA1276","is_ml_official":false,"is_leaf":false},{"id":23,"name":"Electrodomésticos y Aires Ac.","description":null,"created_at":"2025-11-24 15:35:23.723655","updated_at":"2025-11-25 07:07:11.902","ml_category_id":"MLA5726","is_ml_official":false,"is_leaf":false},{"id":24,"name":"Electrónica, Audio y Video","description":null,"created_at":"2025-11-24 15:35:24.127795","updated_at":"2025-11-25 07:07:11.902","ml_category_id":"MLA1000","is_ml_official":false,"is_leaf":false},{"id":25,"name":"Entradas para Eventos","description":null,"created_at":"2025-11-24 15:35:24.589558","updated_at":"2025-11-25 07:07:11.902","ml_category_id":"MLA2547","is_ml_official":false,"is_leaf":false},{"id":26,"name":"Herramientas","description":null,"created_at":"2025-11-24 15:35:24.996187","updated_at":"2025-11-25 07:07:11.902","ml_category_id":"MLA407134","is_ml_official":false,"is_leaf":false},{"id":27,"name":"Hogar, Muebles y Jardín","description":null,"created_at":"2025-11-24 15:35:25.39951","updated_at":"2025-11-25 07:07:11.902","ml_category_id":"MLA1574","is_ml_official":false,"is_leaf":false},{"id":28,"name":"Industrias y Oficinas","description":null,"created_at":"2025-11-24 15:35:25.800048","updated_at":"2025-11-25 07:07:11.902","ml_category_id":"MLA1499","is_ml_official":false,"is_leaf":false},{"id":29,"name":"Inmuebles","description":null,"created_at":"2025-11-24 15:35:26.204536","updated_at":"2025-11-25 07:07:11.902","ml_category_id":"MLA1459","is_ml_official":false,"is_leaf":false},{"id":30,"name":"Instrumentos Musicales","description":null,"created_at":"2025-11-24 15:35:26.604153","updated_at":"2025-11-25 07:07:11.902","ml_category_id":"MLA1182","is_ml_official":false,"is_leaf":false},{"id":31,"name":"Joyas y Relojes","description":null,"created_at":"2025-11-24 15:35:27.004243","updated_at":"2025-11-25 07:07:11.902","ml_category_id":"MLA3937","is_ml_official":false,"is_leaf":false},{"id":32,"name":"Juegos y Juguetes","description":null,"created_at":"2025-11-24 15:35:27.404351","updated_at":"2025-11-25 07:07:11.902","ml_category_id":"MLA1132","is_ml_official":false,"is_leaf":false},{"id":34,"name":"Música, Películas y Series","description":null,"created_at":"2025-11-24 15:35:28.208047","updated_at":"2025-11-25 07:07:11.902","ml_category_id":"MLA1168","is_ml_official":false,"is_leaf":false},{"id":35,"name":"Ropa y Accesorios","description":null,"created_at":"2025-11-24 15:35:28.608118","updated_at":"2025-11-25 07:07:11.902","ml_category_id":"MLA1430","is_ml_official":false,"is_leaf":false},{"id":40,"name":"Celulares y Smartphones","description":null,"created_at":"2025-11-25 07:06:50.90818","updated_at":"2025-11-25 21:56:04.934","ml_category_id":"MLA1055","is_ml_official":true,"is_leaf":true},{"id":41,"name":"Notebooks","description":null,"created_at":"2025-11-25 07:06:51.663449","updated_at":"2025-11-25 21:56:05.177","ml_category_id":"MLA1652","is_ml_official":true,"is_leaf":true},{"id":42,"name":"Televisores","description":null,"created_at":"2025-11-25 07:06:52.403832","updated_at":"2025-11-25 21:56:05.372","ml_category_id":"MLA1002","is_ml_official":true,"is_leaf":true},{"id":43,"name":"Consolas","description":null,"created_at":"2025-11-25 07:06:53.148059","updated_at":"2025-11-25 21:56:05.567","ml_category_id":"MLA438566","is_ml_official":true,"is_leaf":true},{"id":44,"name":"Heladeras","description":null,"created_at":"2025-11-25 07:06:53.891535","updated_at":"2025-11-25 21:56:05.762","ml_category_id":"MLA398582","is_ml_official":true,"is_leaf":true},{"id":45,"name":"Microondas","description":null,"created_at":"2025-11-25 07:06:54.640031","updated_at":"2025-11-25 21:56:05.943","ml_category_id":"MLA1577","is_ml_official":true,"is_leaf":true},{"id":46,"name":"Lavarropas y Lavasecarropas","description":null,"created_at":"2025-11-25 07:06:55.375902","updated_at":"2025-11-25 21:56:06.131","ml_category_id":"MLA431202","is_ml_official":true,"is_leaf":true},{"id":47,"name":"Aires Acondicionados","description":null,"created_at":"2025-11-25 07:06:56.128133","updated_at":"2025-11-25 21:56:06.319","ml_category_id":"MLA1644","is_ml_official":true,"is_leaf":true},{"id":48,"name":"Zapatillas","description":null,"created_at":"2025-11-25 07:06:56.876203","updated_at":"2025-11-25 21:56:06.508","ml_category_id":"MLA109027","is_ml_official":true,"is_leaf":true},{"id":49,"name":"Vestidos","description":null,"created_at":"2025-11-25 07:06:57.611982","updated_at":"2025-11-25 21:56:06.696","ml_category_id":"MLA373770","is_ml_official":true,"is_leaf":true},{"id":50,"name":"Remeras, Musculosas y Chombas","description":null,"created_at":"2025-11-25 07:06:58.409499","updated_at":"2025-11-25 21:56:06.883","ml_category_id":"MLA109042","is_ml_official":true,"is_leaf":true},{"id":51,"name":"Perfumes","description":null,"created_at":"2025-11-25 07:06:59.152372","updated_at":"2025-11-25 21:56:07.071","ml_category_id":"MLA1271","is_ml_official":true,"is_leaf":true},{"id":52,"name":"Set de Maquillaje","description":null,"created_at":"2025-11-25 07:06:59.899596","updated_at":"2025-11-25 21:56:07.257","ml_category_id":"MLA43686","is_ml_official":true,"is_leaf":true},{"id":53,"name":"Shampoos y Acondicionadores","description":null,"created_at":"2025-11-25 07:07:00.632021","updated_at":"2025-11-25 21:56:07.444","ml_category_id":"MLA414007","is_ml_official":true,"is_leaf":true},{"id":54,"name":"Juegos de Living","description":null,"created_at":"2025-11-25 07:07:01.383343","updated_at":"2025-11-25 21:56:07.631","ml_category_id":"MLA31045","is_ml_official":true,"is_leaf":true},{"id":55,"name":"Juegos de Sommier y Colchón","description":null,"created_at":"2025-11-25 07:07:02.119675","updated_at":"2025-11-25 21:56:07.815","ml_category_id":"MLA1611","is_ml_official":true,"is_leaf":true},{"id":56,"name":"Sillas Gamer","description":null,"created_at":"2025-11-25 07:07:02.84817","updated_at":"2025-11-25 21:56:08.001","ml_category_id":"MLA447782","is_ml_official":true,"is_leaf":true},{"id":57,"name":"Eléctricos","description":null,"created_at":"2025-11-25 07:07:03.591558","updated_at":"2025-11-25 21:56:08.19","ml_category_id":"MLA433672","is_ml_official":true,"is_leaf":true},{"id":58,"name":"Bicicletas","description":null,"created_at":"2025-11-25 07:07:04.335927","updated_at":"2025-11-25 21:56:08.382","ml_category_id":"MLA6143","is_ml_official":true,"is_leaf":true},{"id":59,"name":"Motos","description":null,"created_at":"2025-11-25 07:07:05.084453","updated_at":"2025-11-25 21:56:08.574","ml_category_id":"MLA1763","is_ml_official":true,"is_leaf":true},{"id":60,"name":"Neumáticos de Auto y Camioneta","description":null,"created_at":"2025-11-25 07:07:05.829015","updated_at":"2025-11-25 21:56:08.763","ml_category_id":"MLA22195","is_ml_official":true,"is_leaf":true},{"id":61,"name":"Pastillas de Freno","description":null,"created_at":"2025-11-25 07:07:06.560151","updated_at":"2025-11-25 21:56:08.949","ml_category_id":"MLA61177","is_ml_official":true,"is_leaf":true},{"id":62,"name":"Juegos de Mesa y Cartas","description":null,"created_at":"2025-11-25 07:07:07.296433","updated_at":"2025-11-25 21:56:09.139","ml_category_id":"MLA1161","is_ml_official":true,"is_leaf":true},{"id":63,"name":"Cochecitos para Bebés","description":null,"created_at":"2025-11-25 07:07:08.043815","updated_at":"2025-11-25 21:56:09.322","ml_category_id":"MLA1386","is_ml_official":true,"is_leaf":true},{"id":64,"name":"Otros","description":null,"created_at":"2025-11-25 07:07:08.7925","updated_at":"2025-11-25 21:56:09.515","ml_category_id":"MLA127684","is_ml_official":true,"is_leaf":true},{"id":65,"name":"Alimentos Balanceados","description":null,"created_at":"2025-11-25 07:07:09.537311","updated_at":"2025-11-25 21:56:09.702","ml_category_id":"MLA1087","is_ml_official":true,"is_leaf":true},{"id":66,"name":"Suplementos Alimenticios","description":null,"created_at":"2025-11-25 07:07:10.295961","updated_at":"2025-11-25 21:56:09.89","ml_category_id":"MLA8830","is_ml_official":true,"is_leaf":true},{"id":67,"name":"Asistentes Virtuales","description":null,"created_at":"2025-11-25 07:07:11.044425","updated_at":"2025-11-25 21:56:10.076","ml_category_id":"MLA409415","is_ml_official":true,"is_leaf":true},{"id":68,"name":"Parlantes Portátiles","description":null,"created_at":"2025-11-25 07:07:11.792874","updated_at":"2025-11-25 21:56:10.262","ml_category_id":"MLA8618","is_ml_official":true,"is_leaf":true},{"id":69,"name":"Auriculares","description":null,"created_at":"2025-11-25 07:07:12.536284","updated_at":"2025-11-25 21:56:10.449","ml_category_id":"MLA3697","is_ml_official":true,"is_leaf":true}]